discrete_k_identify/__init__.py
discrete_k_identify/__main__.py
discrete_k_identify/identify.py
autonomous_identification-0.1.3.dist-info/METADATA
autonomous_identification-0.1.3.dist-info/WHEEL
autonomous_identification-0.1.3.dist-info/RECORD
